Modion/gRPC/__init__.py
Modion/gRPC/placeholder.py
modion_grpc-0.0.1.dist-info/LICENSE
modion_grpc-0.0.1.dist-info/METADATA
modion_grpc-0.0.1.dist-info/WHEEL
modion_grpc-0.0.1.dist-info/top_level.txt
modion_grpc-0.0.1.dist-info/RECORD
