Metadata-Version: 2.2
Name: Modion.gRPC
Version: 0.0.1
Summary: gRPC functions for Modion D3PLOT, PRIMER, REPORTER and T/HIS
Author: Miles Thornton
Maintainer-email: dyna.support@arup.com
License: MIT License
Project-URL: Homepage, https://www.oasys-software.com/dyna/
Keywords: Modion,gRPC
Requires-Python: >=3.7
License-File: LICENSE
